quri_vm/__init__.py
quri_vm/py.typed
quri_vm/simulator.py
quri_vm/vm.py
quri_vm/vm_backend.py
quri_vm-0.24.1.dist-info/LICENSE
quri_vm-0.24.1.dist-info/METADATA
quri_vm-0.24.1.dist-info/WHEEL
quri_vm-0.24.1.dist-info/RECORD
