Metadata-Version: 2.1
Name: quri-vm
Version: 0.24.1
Summary: 
Author: QunaSys
Requires-Python: >=3.10,<4
Classifier: Programming Language :: Python :: 3
Classifier: Programming Language :: Python :: 3.10
Classifier: Programming Language :: Python :: 3.11
Classifier: Programming Language :: Python :: 3.12
Requires-Dist: quri-parts-circuit
Requires-Dist: quri-parts-qulacs
